yc_django_celery/__init__.py
yc_django_celery/admin.py
yc_django_celery/apps.py
yc_django_celery/models.py
yc_django_celery/settings.py
yc_django_celery/tasks.py
yc_django_celery/tests.py
yc_django_celery/urls.py
yc_django_celery/views.py
yc_django_celery/api/__init__.py
yc_django_celery/api/celery_test.py
yc_django_celery/migrations/__init__.py
yc_django_celery-0.0.1.dist-info/LICENSE
yc_django_celery-0.0.1.dist-info/METADATA
yc_django_celery-0.0.1.dist-info/WHEEL
yc_django_celery-0.0.1.dist-info/top_level.txt
yc_django_celery-0.0.1.dist-info/RECORD
